weatherkit/__init__.py
weatherkit/models.py
weatherkit/weatherkit.py
weatherkit_python-1.0.1.dist-info/LICENSE
weatherkit_python-1.0.1.dist-info/METADATA
weatherkit_python-1.0.1.dist-info/WHEEL
weatherkit_python-1.0.1.dist-info/top_level.txt
weatherkit_python-1.0.1.dist-info/RECORD
