Metadata-Version: 2.1
Name: weatherkit-python
Version: 1.0.1
Summary: A Python interface for Apple's WeatherKit APIs
Home-page: https://github.com/greencoder/weatherkit-python
Author: Scott Newman
Author-email: snewman18@gmail.com
License: MIT
Requires-Python: >=3.6
License-File: LICENSE
Requires-Dist: jsonpickle (>=1.4.3)
Requires-Dist: cryptography (>=38)
Requires-Dist: pyjwt (>=2.6.0)
Requires-Dist: requests (>=2.28.1)
